{
  "sections": {
    "main": {
      "type": "page-candy-museum",
      "blocks": {
        "4636500e-73d1-494d-b6a1-ad359cc54daa": {
          "type": "candy",
          "settings": {
            "candy_title": "Baby Ruth",
            "main_image": "shopify:\/\/shop_images\/museum-image_225x1902x2_edff666e-80d2-4e8c-a8eb-13480ef9e11a.png",
            "hover_image": "shopify:\/\/shop_images\/museum-image-hoverd_225x1902x.png",
            "cta_url": "shopify:\/\/collections\/walk-the-candy-aisle-baby-ruth"
          }
        },
        "882153cc-ad3f-49e7-9a53-ee527ef75b23": {
          "type": "candy",
          "settings": {
            "candy_title": "BIT-O-HONEY",
            "main_image": "shopify:\/\/shop_images\/bitOHoney-up_1_225x1902x2.png",
            "hover_image": "shopify:\/\/shop_images\/bitOHoney-over_1_225x1902x.jpg",
            "cta_url": "shopify:\/\/collections\/walk-the-candy-aisle-bit-o-honey"
          }
        },
        "b1e2873d-46f6-4020-b2fe-cb4f4e549282": {
          "type": "candy",
          "settings": {
            "candy_title": "BIG TIME",
            "main_image": "shopify:\/\/shop_images\/big-time-candy-bar2_1_225x1902x2.png",
            "hover_image": "shopify:\/\/shop_images\/big-time-candy-bar-over_1_225x1902x.jpg",
            "cta_url": "shopify:\/\/pages\/discontinued-candy"
          }
        },
        "30839829-22a7-45c8-9c85-e32350982f9c": {
          "type": "candy",
          "settings": {
            "candy_title": "Bun",
            "main_image": "shopify:\/\/shop_images\/bun-up_1_225x1902x2.png",
            "hover_image": "shopify:\/\/shop_images\/bun-over_1_225x1902x.jpg",
            "cta_url": "shopify:\/\/collections\/walk-the-candy-aisle-bun-candy-bar"
          }
        },
        "b33fdb98-93c2-4535-8329-d60cc14f26fc": {
          "type": "candy",
          "settings": {
            "candy_title": "BUTTERFINGER",
            "main_image": "shopify:\/\/shop_images\/butterfinger-up_1_225x1902x2.png",
            "hover_image": "shopify:\/\/shop_images\/butterfinger-over_1_225x1902x.jpg",
            "cta_url": "shopify:\/\/collections\/walk-the-candy-aisle-butterfingers"
          }
        },
        "f9c6981c-185f-4e79-b440-bad4e78dcce8": {
          "type": "candy",
          "settings": {
            "candy_title": "BUTTER NUT",
            "main_image": "shopify:\/\/shop_images\/butter-nut-candy-bar_1_225x1902x2.png",
            "hover_image": "shopify:\/\/shop_images\/butter-nut-candy-bar-over_1_225x1902x.jpg",
            "cta_url": "shopify:\/\/pages\/discontinued-candy"
          }
        },
        "9fb77383-6262-4e0d-90ae-890e873c9d5c": {
          "type": "candy",
          "settings": {
            "candy_title": "CARAVELLE",
            "main_image": "shopify:\/\/shop_images\/caravelle-candy-bar_1_225x1902x2.png",
            "hover_image": "shopify:\/\/shop_images\/caravelle-candy-bar-over_1_225x1902x.jpg",
            "cta_url": "shopify:\/\/pages\/discontinued-candy"
          }
        },
        "63b7f897-a299-44b6-a7ad-a8e04833fd31": {
          "type": "candy",
          "settings": {
            "candy_title": "CANDY CIGARETTES",
            "main_image": "shopify:\/\/shop_images\/candyCigarettes-up_1_225x1902x2.png",
            "hover_image": "shopify:\/\/shop_images\/candyCigarettes-over_1_225x1902x.jpg",
            "cta_url": "shopify:\/\/collections\/walk-the-candy-aisle-candy-cigarettes"
          }
        },
        "d8dc6a88-a284-4bd3-8ea3-e34fd4179ade": {
          "type": "candy",
          "settings": {
            "candy_title": "CHARLESTON CHEW",
            "main_image": "shopify:\/\/shop_images\/charlestonChew-up_1_225x1902x2.png",
            "hover_image": "shopify:\/\/shop_images\/charlestonChew-over_1_225x1902x.jpg",
            "cta_url": "shopify:\/\/collections\/walk-the-candy-aisle-charleston-chew"
          }
        },
        "f80bb5fe-30bd-46b8-8b07-24fd81b56d1e": {
          "type": "candy",
          "settings": {
            "candy_title": "CHARMS POP",
            "main_image": "shopify:\/\/shop_images\/charmsPop-up_1_225x1902x2.png",
            "hover_image": "shopify:\/\/shop_images\/charmsPop-over_1_225x1902x.jpg",
            "cta_url": "shopify:\/\/collections\/walk-the-candy-aisle-charms-sweet-pops"
          }
        },
        "77589bb3-f43b-449d-9084-ccc8228d8e88": {
          "type": "candy",
          "settings": {
            "candy_title": "CHICKEN BONES",
            "main_image": "shopify:\/\/shop_images\/chicken-bones_1_225x1902x2.png",
            "hover_image": "shopify:\/\/shop_images\/chicken-bones-over_1_225x1902x.jpg",
            "cta_url": "shopify:\/\/pages\/discontinued-candy"
          }
        },
        "4de71f2a-18e0-4db7-8320-23478f7f363d": {
          "type": "candy",
          "settings": {
            "candy_title": "CHICKEN DINNER",
            "main_image": "shopify:\/\/shop_images\/chicken-dinner-candy-bar_1_225x1902x2.png",
            "hover_image": "shopify:\/\/shop_images\/chicken-dinner-candy-bar-over_1_225x1902x.jpg",
            "cta_url": "shopify:\/\/pages\/discontinued-candy"
          }
        },
        "9b879937-4ea8-473f-8b8a-35f011afad6b": {
          "type": "candy",
          "settings": {
            "candy_title": "CHICK-O-STICK",
            "main_image": "shopify:\/\/shop_images\/chickOSticks-up_fbc1a6e4-003e-499f-a038-8d8c37ba008e_225x1902x2.png",
            "hover_image": "shopify:\/\/shop_images\/chickOSticks-over_79afdbe8-9e87-4afc-8853-4ef579a919e6_225x1902x.jpg",
            "cta_url": "shopify:\/\/collections\/walk-the-candy-aisle-chick-o-sticks"
          }
        },
        "9a562ec7-41c7-40ee-96b3-afcc959be225": {
          "type": "candy",
          "settings": {
            "candy_title": "CLARK",
            "main_image": "shopify:\/\/shop_images\/clark-up_0535f4b9-4ac5-4bed-863d-b912c1948b60_225x1902x2.png",
            "hover_image": "shopify:\/\/shop_images\/clark-over_b8cbceb6-7ab8-4fb3-9a9c-cb5be8d1a3e8_225x1902x.jpg",
            "cta_url": "shopify:\/\/collections\/walk-the-candy-aisle-clark-bars"
          }
        },
        "673cb20a-a396-454b-a9be-a9b148003da6": {
          "type": "candy",
          "settings": {
            "candy_title": "CUP-O-GOLD",
            "main_image": "shopify:\/\/shop_images\/cup-o-gold_ce8a640d-10b4-4f99-9561-3d93ea6e5907_225x1902x2.png",
            "hover_image": "shopify:\/\/shop_images\/cup-o-gold-over_6a7ab840-bdfa-4466-9969-7552ce0fc09a_225x1902x.jpg",
            "cta_url": "shopify:\/\/collections\/walk-the-candy-aisle-cup-o-gold"
          }
        },
        "709be1cf-af79-4f53-a4e0-3e8f57cdef7a": {
          "type": "candy",
          "settings": {
            "candy_title": "DENVER SANDWHICH",
            "main_image": "shopify:\/\/shop_images\/denverSandwich-up_e6b4d07d-7cdc-4a7b-a79c-75d8399e4856_225x1902x2.png",
            "hover_image": "shopify:\/\/shop_images\/denverSandwich-over_9ac8f0c8-3c7a-418c-89f7-18f91165d8ea_225x1902x.jpg",
            "cta_url": "shopify:\/\/pages\/discontinued-candy"
          }
        },
        "94bf8292-bc92-451e-ac50-68d0c42abace": {
          "type": "candy",
          "settings": {
            "candy_title": "DUM DUM POPS",
            "main_image": "shopify:\/\/shop_images\/dumDumPops-up_e77f8a05-d87a-4b18-a2c0-9acafe10867c_225x1902x2.png",
            "hover_image": "shopify:\/\/shop_images\/dumDumPops-over_b5c5b267-31d8-48f7-97cd-ed52e6576140_225x1902x.jpg",
            "cta_url": "shopify:\/\/collections\/walk-the-candy-aisle-dum-dum-pops"
          }
        },
        "03b205cb-ba9b-48e6-bced-19bfda923ab6": {
          "type": "candy",
          "settings": {
            "candy_title": "FIFTH AVENUE",
            "main_image": "shopify:\/\/shop_images\/FifthAvenue-up_4d80f87c-b7f6-43a1-bb9f-513a855724e1_225x1902x2.png",
            "hover_image": "shopify:\/\/shop_images\/FifthAvenue-over_47f49b78-aec2-468c-90cd-5b43c06aa3fe_225x1902x.jpg",
            "cta_url": "shopify:\/\/collections\/walk-the-candy-aisle-5th-avenue"
          }
        },
        "f113b44d-92a5-4f86-b06d-8c4f85f8c713": {
          "type": "candy",
          "settings": {
            "candy_title": "FOREVER YOURS",
            "main_image": "shopify:\/\/shop_images\/foreverYours-up_f1675ee6-8f27-49fe-9358-ac6573bd3532_225x1902x2.png",
            "hover_image": "shopify:\/\/shop_images\/foreverYours-over_a28a215d-3a98-44f1-a747-4bede2843c1e_225x1902x.jpg",
            "cta_url": "shopify:\/\/products\/milkly-way-midnight-box"
          }
        },
        "c1392dbd-b104-47a2-bc1e-fc8579644e06": {
          "type": "candy",
          "settings": {
            "candy_title": "GOLDENBERG'S PEANUT CHEWS",
            "main_image": "shopify:\/\/shop_images\/goldenberg-up_95c43672-2851-449a-a2ec-fce58990db11_225x1902x2.png",
            "hover_image": "shopify:\/\/shop_images\/goldenberg-over_2170485f-4071-42d0-964c-235df654c287_225x1902x.jpg",
            "cta_url": "shopify:\/\/collections\/walk-the-candy-aisle-goldenberg-s-peanut-chews"
          }
        },
        "838962e1-fab4-460a-bc44-ce9c48eb1638": {
          "type": "candy",
          "settings": {
            "candy_title": "HOLLYWOOD",
            "main_image": "shopify:\/\/shop_images\/hollywood-up_b528f703-efe7-4bc3-a0b2-043d4c4dd076_225x1902x2.png",
            "hover_image": "shopify:\/\/shop_images\/hollywood-over_bce27b68-24f7-4b94-90cf-0402f79c8cdb_225x1902x.jpg",
            "cta_url": "shopify:\/\/pages\/discontinued-candy"
          }
        },
        "296847dd-8631-4e16-ad6c-6ea8eaa2065f": {
          "type": "candy",
          "settings": {
            "candy_title": "KITS TAFFY",
            "main_image": "shopify:\/\/shop_images\/kits-taffy_8d1523f4-812a-49ed-b729-65ff10867a4a_225x1902x2.png",
            "hover_image": "shopify:\/\/shop_images\/kits-taffy-over_ff8a71da-81de-4cdd-8546-4ecab825758d_225x1902x.jpg",
            "cta_url": "shopify:\/\/collections\/walk-the-candy-aisle-kits-taffy"
          }
        },
        "2c37eee9-4bbe-472f-b76c-feeb12a8e760": {
          "type": "candy",
          "settings": {
            "candy_title": "MILK DUDS",
            "main_image": "shopify:\/\/shop_images\/milkDuds-up_029ea78d-045f-4534-9375-2cde547444f5_225x1902x2.png",
            "hover_image": "shopify:\/\/shop_images\/milkDuds-over_3e5db562-eac8-44e1-88cc-4fd6aa5f06e0_225x1902x.jpg",
            "cta_url": "shopify:\/\/collections\/walk-the-candy-aisle-milk-duds"
          }
        },
        "4c90b01c-b99a-4dc0-8c97-703d056c8203": {
          "type": "candy",
          "settings": {
            "candy_title": "MILKSHAKE",
            "cta_url": ""
          }
        },
        "5966505c-d873-4908-8846-a3e7a73ebc49": {
          "type": "candy",
          "settings": {
            "candy_title": "MILKY WAY",
            "cta_url": ""
          }
        },
        "a4b0c712-bc82-4579-9e25-ad51d0768b18": {
          "type": "candy",
          "settings": {
            "candy_title": "OH HENRY",
            "cta_url": ""
          }
        },
        "a09e1819-adb8-4047-aed9-be8b7aa93186": {
          "type": "candy",
          "settings": {
            "candy_title": "PAY DAY",
            "cta_url": ""
          }
        },
        "2470b7f3-a3db-4cf5-8962-e22291fd2363": {
          "type": "candy",
          "settings": {
            "candy_title": "POWERHOUSE",
            "cta_url": ""
          }
        },
        "632e4636-11cd-4461-b003-0832807cc99e": {
          "type": "candy",
          "settings": {
            "candy_title": "SALTED NUT ROLLS",
            "cta_url": ""
          }
        },
        "10e85627-5102-485e-ada4-c22cb8c4b8db": {
          "type": "candy",
          "settings": {
            "candy_title": "SEVEN UP",
            "cta_url": ""
          }
        },
        "55e79e83-0675-4a89-9eff-45eacdb2917a": {
          "type": "candy",
          "settings": {
            "candy_title": "SKY BAR",
            "cta_url": ""
          }
        },
        "07a12626-f4f1-41b1-a9fa-60ac6a934bfb": {
          "type": "candy",
          "settings": {
            "candy_title": "SNICKERS",
            "cta_url": ""
          }
        },
        "7c28eeb0-0459-446f-bf3c-8030efc4040b": {
          "type": "candy",
          "settings": {
            "candy_title": "TOOTSIE ROLL POPS",
            "cta_url": ""
          }
        },
        "ff10b417-0a65-4ff6-a9de-5f66e8e488b8": {
          "type": "candy",
          "settings": {
            "candy_title": "VALOMILK",
            "cta_url": ""
          }
        },
        "7ec694c8-d03a-4cf2-b3f6-42b3b7913f16": {
          "type": "candy",
          "settings": {
            "candy_title": "ZAGNUT",
            "cta_url": ""
          }
        },
        "f600f27c-d038-4228-9ab4-b20725088461": {
          "type": "candy",
          "settings": {
            "candy_title": "ZERO",
            "cta_url": ""
          }
        }
      },
      "block_order": [
        "4636500e-73d1-494d-b6a1-ad359cc54daa",
        "882153cc-ad3f-49e7-9a53-ee527ef75b23",
        "b1e2873d-46f6-4020-b2fe-cb4f4e549282",
        "30839829-22a7-45c8-9c85-e32350982f9c",
        "b33fdb98-93c2-4535-8329-d60cc14f26fc",
        "f9c6981c-185f-4e79-b440-bad4e78dcce8",
        "9fb77383-6262-4e0d-90ae-890e873c9d5c",
        "63b7f897-a299-44b6-a7ad-a8e04833fd31",
        "d8dc6a88-a284-4bd3-8ea3-e34fd4179ade",
        "f80bb5fe-30bd-46b8-8b07-24fd81b56d1e",
        "77589bb3-f43b-449d-9084-ccc8228d8e88",
        "4de71f2a-18e0-4db7-8320-23478f7f363d",
        "9b879937-4ea8-473f-8b8a-35f011afad6b",
        "9a562ec7-41c7-40ee-96b3-afcc959be225",
        "673cb20a-a396-454b-a9be-a9b148003da6",
        "709be1cf-af79-4f53-a4e0-3e8f57cdef7a",
        "94bf8292-bc92-451e-ac50-68d0c42abace",
        "03b205cb-ba9b-48e6-bced-19bfda923ab6",
        "f113b44d-92a5-4f86-b06d-8c4f85f8c713",
        "c1392dbd-b104-47a2-bc1e-fc8579644e06",
        "838962e1-fab4-460a-bc44-ce9c48eb1638",
        "296847dd-8631-4e16-ad6c-6ea8eaa2065f",
        "2c37eee9-4bbe-472f-b76c-feeb12a8e760",
        "4c90b01c-b99a-4dc0-8c97-703d056c8203",
        "5966505c-d873-4908-8846-a3e7a73ebc49",
        "a4b0c712-bc82-4579-9e25-ad51d0768b18",
        "a09e1819-adb8-4047-aed9-be8b7aa93186",
        "2470b7f3-a3db-4cf5-8962-e22291fd2363",
        "632e4636-11cd-4461-b003-0832807cc99e",
        "10e85627-5102-485e-ada4-c22cb8c4b8db",
        "55e79e83-0675-4a89-9eff-45eacdb2917a",
        "07a12626-f4f1-41b1-a9fa-60ac6a934bfb",
        "7c28eeb0-0459-446f-bf3c-8030efc4040b",
        "ff10b417-0a65-4ff6-a9de-5f66e8e488b8",
        "7ec694c8-d03a-4cf2-b3f6-42b3b7913f16",
        "f600f27c-d038-4228-9ab4-b20725088461"
      ],
      "settings": {
      }
    },
    "1653969137646964d3": {
      "type": "newsletter",
      "blocks": {
        "165396913737aba1ff-0": {
          "type": "heading",
          "settings": {
            "heading": "Subscribe to our emails",
            "heading_size": "h1"
          }
        },
        "165396913737aba1ff-1": {
          "type": "paragraph",
          "settings": {
            "text": "<p>Be the first to know about new collections and exclusive offers.<\/p>"
          }
        },
        "165396913737aba1ff-2": {
          "type": "email_form",
          "settings": {
            "btn_text": "Sign up"
          }
        }
      },
      "block_order": [
        "165396913737aba1ff-0",
        "165396913737aba1ff-1",
        "165396913737aba1ff-2"
      ],
      "settings": {
        "style": "old",
        "color_scheme": "background-1",
        "full_width": true,
        "padding_top": 50,
        "padding_bottom": 50
      }
    }
  },
  "order": [
    "main",
    "1653969137646964d3"
  ]
}
